{
  "hash": "fa3ea37eb2175334caec6bd9dd42e0a9",
  "result": {
    "engine": "knitr",
    "markdown": "---\ntitle: \"Answers: Introduction to linear regression\"\nauthor: \"Flora Green\"\nabstract-title: Summary\nabstract: Answers to questions relating to the guide on introduction to linear regression.\n---\n\n*These are the answers to [Questions: Introduction to linear regression](../questions/qs-linearregression.qmd).*\n\n**Please attempt the questions before reading these answers!**\n\n## Q1 {-}\n\n1.1. $\\alpha$ is the $y$-intercept of the regression line $\\mathbb{E}(Y) = \\alpha + \\beta x$.\n\n1.2. $\\beta$ is the gradient of the regression line $\\mathbb{E}(Y) = \\alpha + \\beta x$.\n\n\n## Q2 {-}\n\n2.1. A residual is the difference between the observed value $y_i$ and the estimated value $\\mathbb{E}(Y_{i})$. \n\n2.2. It minimizes the squared sum of the residuals to find the optimal regression line for a sample of data.\n\n## Q3 {-}\n\n3.1.  Here, $\\hat{\\alpha} = 146.6853$.\n\n3.2.  Here, $\\hat{\\beta} = 1.7044$.\n\n3.3.  $\\mathbb{E}(Y) = \\alpha + \\beta x = \\hat{\\alpha} + \\hat{\\beta} x = 146.6853 + 1.7044 x$\n\n3.4. The $R^2$ coefficient of determination is $0.2691$, which suggests that the response variable is not well modelled by a linear model of the explanatory variable.\n\nPlease note that for this question, the following `R` code was used. It is recommended that you use [Calculator: Simple linear regression](../apps/calculators/c-simplelinearregression.qmd) or statistical software like this to do these calculations, as these can be very tedious to do by hand. \n\n```{.r}\nconfectionery = data.frame(customers=c(43,54,65,42,68,49, \n63,57,71,47,75,67),sweets=c(188,197,215,217,233,244,254,256,\n274,286,291,300))\nmodel=lm(sweets~customers,data=confectionery)\nsummary(model)\n\nplot(confectionery$customers, confectionery$sweets,\n     pch = 19, col = \"#3f68b6\",\n     xlab = \"Number of customers\",\n     ylab = \"Sweets sold\")\n\nabline(model, col = \"#db4315\", lwd = 2)\n```\n\n**Code output:**\n\n\n::: {.cell}\n::: {.cell-output .cell-output-stdout}\n\n```\n\nCall:\nlm(formula = sweets ~ customers, data = confectionery)\n\nResiduals:\n    Min      1Q  Median      3Q     Max \n-42.471 -30.181   3.121  14.471  59.208 \n\nCoefficients:\n            Estimate Std. Error t value Pr(>|t|)  \n(Intercept) 146.6853    52.7694   2.780   0.0195 *\ncustomers     1.7044     0.8882   1.919   0.0839 .\n---\nSignif. codes:  0 '***' 0.001 '**' 0.01 '*' 0.05 '.' 0.1 ' ' 1\n\nResidual standard error: 33.36 on 10 degrees of freedom\nMultiple R-squared:  0.2691,\tAdjusted R-squared:  0.1961 \nF-statistic: 3.683 on 1 and 10 DF,  p-value: 0.08395\n```\n\n\n:::\n\n::: {.cell-output-display}\n![](as-linearregression_files/figure-docx/unnamed-chunk-1-1.png)\n:::\n:::\n\n\n<!-- ## Q2 {-} -->\n\n<!-- **2.1.** Yes, because the samples were taken from different days. -->\n\n<!-- **2.2.** No, because the points stray from the dashed line in the Q-Q plot. -->\n\n<!-- **2.3.** No, because the red line is quite curved. -->\n\n<!-- **2.4.** Yes, because the red line in the scale-location line is mostly flat. -->\n\n<!-- **2.5** No, because the above assumptions do not all hold. -->\n\n<!-- ## Q3 {-} -->\n\n<!-- **3.1.** A 95% confidence interval for $\\hat{\\alpha}$ is given by $\\hat{\\alpha} \\pm t_{n-2; 1 - \\frac{5}{2}} \\sqrt{S^2 \\left (\\frac{1}{n} + \\frac{\\bar{x}^2}{SS_{XX}} \\right)} = (29.1078018, 264.262820)$. -->\n\n<!-- **3.2.** A 95% confidence interval for $\\hat{\\beta}$ is given by $\\hat{\\beta} \\pm t_{n-2; 1 - \\frac{5}{2}} \\sqrt{S^2 \\left (\\frac{1}{n} + \\frac{\\bar{x}^2}{SS_{XX}} \\right)} = (-0.2745477, 3.683325)$. -->\n\n<!-- **3.3.** A 90% confidence interval for $\\hat{\\alpha}$ is given by $\\hat{\\alpha} \\pm t_{n-2; 1 - \\frac{10}{2}} \\sqrt{S^2 \\left (\\frac{1}{n} + \\frac{\\bar{x}^2}{SS_{XX}} \\right)} = (51.04285847, 242.327763)$. -->\n\n<!-- **3.4.** A 90% confidence interval for $\\hat{\\beta}$ is given by $\\hat{\\beta} \\pm t_{n-2; 1 - \\frac{10}{2}} \\sqrt{S^2 \\left (\\frac{1}{n} + \\frac{\\bar{x}^2}{SS_{XX}} \\right)} = (0.09463917, 3.314138)$. -->\n---\n\n---\n\n## Version history and licensing {-}\n\nv1.0: initial version created 12/25 by Flora Green as part of a University of St Andrews VIP project.\n\n[This work is licensed under CC BY-NC-SA 4.0.](https://creativecommons.org/licenses/by-nc-sa/4.0/?ref=chooser-v1)\n",
    "supporting": [],
    "filters": [
      "rmarkdown/pagebreak.lua"
    ],
    "includes": {},
    "engineDependencies": {},
    "preserve": null,
    "postProcess": false
  }
}